django_koldar_utils/__init__.py
django_koldar_utils/version.py
django_koldar_utils/django_toolbox/AbstractDjangoBackend.py
django_koldar_utils/django_toolbox/AbstractDjangoField.py
django_koldar_utils/django_toolbox/AbstractDjangoMiddleware.py
django_koldar_utils/django_toolbox/AbstractValidator.py
django_koldar_utils/django_toolbox/ApplicationProperty.py
django_koldar_utils/django_toolbox/Orm.py
django_koldar_utils/django_toolbox/__init__.py
django_koldar_utils/django_toolbox/auth_decorators.py
django_koldar_utils/django_toolbox/django_helpers.py
django_koldar_utils/django_toolbox/filters_helpers.py
django_koldar_utils/django_toolbox/managers.py
django_koldar_utils/django_toolbox/permissions_helpers.py
django_koldar_utils/django_toolbox/commands/__init__.py
django_koldar_utils/django_toolbox/conf/DictSettingMergerAppConf.py
django_koldar_utils/django_toolbox/conf/__init__.py
django_koldar_utils/django_toolbox/conf/conf.py
django_koldar_utils/django_toolbox/fields/ArrowDateField.py
django_koldar_utils/django_toolbox/fields/ArrowDateFieldForm.py
django_koldar_utils/django_toolbox/fields/ArrowDurationField.py
django_koldar_utils/django_toolbox/fields/ArrowDurationFieldForm.py
django_koldar_utils/django_toolbox/fields/ArrowField.py
django_koldar_utils/django_toolbox/fields/ArrowFieldForm.py
django_koldar_utils/django_toolbox/fields/PhotoField.py
django_koldar_utils/django_toolbox/fields/__init__.py
django_koldar_utils/django_toolbox/models/AbstractGenericUser.py
django_koldar_utils/django_toolbox/models/AbstractModelMetaclass.py
django_koldar_utils/django_toolbox/models/__init__.py
django_koldar_utils/django_toolbox/models/mixins/ActiveMixIn.py
django_koldar_utils/django_toolbox/models/mixins/ArrowAuditMixin.py
django_koldar_utils/django_toolbox/models/mixins/AuditMixIn.py
django_koldar_utils/django_toolbox/models/mixins/__init__.py
django_koldar_utils/django_toolbox/models/mixins/users/DatabaselessPermissionsMixin.py
django_koldar_utils-2.111.14.dist-info/LICENSE.md
django_koldar_utils-2.111.14.dist-info/METADATA
django_koldar_utils-2.111.14.dist-info/WHEEL
django_koldar_utils-2.111.14.dist-info/top_level.txt
django_koldar_utils-2.111.14.dist-info/RECORD
