Metadata-Version: 2.1
Name: django-koldar-utils
Version: 2.111.14
Summary: Some stuff that i used when developing with django_toolbox
Home-page: https://github.com/Koldar/django-koldar-common-apps
Author: Massimo Bono
Author-email: massimobono1@gmail.com
License: MIT
Keywords: utils
Platform: UNKNOWN
Classifier: Programming Language :: Python :: 3
Classifier: Operating System :: OS Independent
Requires-Python: >=3.6
License-File: LICENSE.md
License-File: Makefile
License-File: PASSWORD
License-File: PMakeupfile.py
License-File: README.md
License-File: TWINE_PYPI_PASSWORD
License-File: make.bat
License-File: pmakeup-cache.json
License-File: requirements.txt
License-File: setup.py
Requires-Dist: alabaster (>=0.7.12)
Requires-Dist: aniso8601 (>=8.1.1)
Requires-Dist: arrow (>=1.1.0)
Requires-Dist: asgiref (>=3.3.4)
Requires-Dist: Babel (>=2.9.1)
Requires-Dist: certifi (>=2021.5.30)
Requires-Dist: chardet (>=4.0.0)
Requires-Dist: colorama (>=0.4.4)
Requires-Dist: datasize (>=1.0.0)
Requires-Dist: decorator (>=4.4.2)
Requires-Dist: Django (>=3.2.7)
Requires-Dist: django-appconf (>=1.0.4)
Requires-Dist: django-currentuser (>=0.5.3)
Requires-Dist: django-environ (>=0.4.5)
Requires-Dist: django-filter (>=2.4.0)
Requires-Dist: django-graphql-jwt (>=0.3.2)
Requires-Dist: django-polymorphic (>=3.0.0)
Requires-Dist: djangorestframework (>=3.12.4)
Requires-Dist: docutils (>=0.17.1)
Requires-Dist: gitdb (>=4.0.7)
Requires-Dist: GitPython (>=3.1.18)
Requires-Dist: graphene (>=3.0b7)
Requires-Dist: graphene-django (>=3.0.0b7)
Requires-Dist: graphene-django-extras (>=0.5.1)
Requires-Dist: graphql-core (>=3.1.5)
Requires-Dist: graphql-relay (>=3.1.0)
Requires-Dist: idna (>=2.10)
Requires-Dist: imagesize (>=1.2.0)
Requires-Dist: inflect (>=5.3.0)
Requires-Dist: inflection (>=0.5.1)
Requires-Dist: Jinja2 (>=3.0.1)
Requires-Dist: jmespath (>=0.10.0)
Requires-Dist: koldar-utils (>=2.103.0)
Requires-Dist: m2r (>=0.2.1)
Requires-Dist: MarkupSafe (>=2.0.1)
Requires-Dist: mistune (>=0.8.4)
Requires-Dist: networkx (>=2.5.1)
Requires-Dist: packaging (>=21.0)
Requires-Dist: Pillow (>=8.3.1)
Requires-Dist: promise (>=2.3)
Requires-Dist: pydot (>=1.4.2)
Requires-Dist: Pygments (>=2.10.0)
Requires-Dist: PyJWT (>=2.1.0)
Requires-Dist: pyparsing (>=2.4.7)
Requires-Dist: python-dateutil (>=2.8.1)
Requires-Dist: pytz (>=2021.1)
Requires-Dist: requests (>=2.25.1)
Requires-Dist: Rx (>=1.6.1)
Requires-Dist: semantic-version (>=2.8.5)
Requires-Dist: singledispatch (>=3.6.1)
Requires-Dist: six (>=1.16.0)
Requires-Dist: smmap (>=4.0.0)
Requires-Dist: snowballstemmer (>=2.1.0)
Requires-Dist: Sphinx (>=4.2.0)
Requires-Dist: sphinx-autodoc-typehints (>=1.12.0)
Requires-Dist: sphinx-rtd-theme (>=1.0.0)
Requires-Dist: sphinxcontrib-applehelp (>=1.0.2)
Requires-Dist: sphinxcontrib-devhelp (>=1.0.2)
Requires-Dist: sphinxcontrib-htmlhelp (>=2.0.0)
Requires-Dist: sphinxcontrib-jsmath (>=1.0.1)
Requires-Dist: sphinxcontrib-qthelp (>=1.0.3)
Requires-Dist: sphinxcontrib-serializinghtml (>=1.1.5)
Requires-Dist: sqlparse (>=0.4.2)
Requires-Dist: stringcase (>=1.2.0)
Requires-Dist: text-unidecode (>=1.3)
Requires-Dist: urllib3 (>=1.26.5)
Provides-Extra: docs
Requires-Dist: sphinx ; extra == 'docs'
Requires-Dist: sphinx-rtd-theme ; extra == 'docs'
Requires-Dist: sphinx-autodoc-typehints ; extra == 'docs'
Provides-Extra: test
Requires-Dist: pytest ; extra == 'test'
Requires-Dist: mock ; extra == 'test'
